README.md
setup.cfg
setup.py
bin/nvfan
nvfan/__init__.py
nvfan/curve.py
nvfan/decorators.py
nvfan/gpu.py
nvfan/utils.py
nvfan.egg-info/PKG-INFO
nvfan.egg-info/SOURCES.txt
nvfan.egg-info/dependency_links.txt
nvfan.egg-info/top_level.txt