Metadata-Version: 2.1
Name: nvfan
Version: 0.3.0
Summary: Control Nvidia GPU fan in your python script.
Home-page: https://github.com/magnusja/nvfan
Author: Magnus Jahnen
Author-email: magnus@jahnen.me
License: UNKNOWN
Project-URL: Bug Reports, https://github.com/magnusja/nvfan/issues
Project-URL: Home Page, https://github.com/magnusja/nvfan
Keywords: machinelearning ai pytorch tensorflow torch nvidia gpu fan
Platform: UNKNOWN
Classifier: Development Status :: 4 - Beta
Classifier: Intended Audience :: Developers
Classifier: Intended Audience :: Science/Research
Classifier: Topic :: Scientific/Engineering :: Artificial Intelligence
Classifier: Programming Language :: Python :: 3.5
Classifier: Programming Language :: Python :: 3.6
Classifier: Programming Language :: Python :: 3.7
Requires-Python: >=3
